{
"instructions_readme": "1) Open Chrome, 2) go to chrome://tracing, 3) click Load, 4) navigate to this file.",

"traceEvents":[
{ "pid": 1, "tid": 1, "ph": "M", "name": "thread_name", "args": { "name": "" } },
{ "pid": 1, "tid": 1, "ts": 693.1, "dur": 16816208, "ph": "X", "name": "il2cpp.exe", "args": { "durationMS": 16816.208, "detail": "" } },
{ "pid": 1, "tid": 1, "ts": 22344.3, "dur": 16794516.8, "ph": "X", "name": "ConvertAssemblies", "args": { "durationMS": 16794.5168, "detail": "" } },
{ "pid": 1, "tid": 1, "ts": 46988.6, "dur": 88791.7, "ph": "X", "name": "Collect assemblies to convert", "args": { "durationMS": 88.7917, "detail": "" } },
{ "pid": 1, "tid": 1, "ts": 136097.6, "dur": 37884, "ph": "X", "name": "RegisterCorlib", "args": { "durationMS": 37.884, "detail": "" } },
{ "pid": 1, "tid": 1, "ts": 174143, "dur": 52913.4, "ph": "X", "name": "PreProcessIL", "args": { "durationMS": 52.9134, "detail": "" } },
{ "pid": 1, "tid": 1, "ts": 174144.3, "dur": 8294.8, "ph": "X", "name": "Inject base types and finalizers into COM and Windows Runtime types", "args": { "durationMS": 8.2948, "detail": "" } },
{ "pid": 1, "tid": 1, "ts": 174344.5, "dur": 6246.5, "ph": "X", "name": "ModifyCOMAndWindowsRuntimeTypes in assembly", "args": { "durationMS": 6.2465, "detail": "mscorlib" } },
{ "pid": 1, "tid": 1, "ts": 182440.9, "dur": 44615.3, "ph": "X", "name": "ApplyDefaultMarshalAsAttribute", "args": { "durationMS": 44.6153, "detail": "" } },
{ "pid": 1, "tid": 1, "ts": 182591.2, "dur": 26636.3, "ph": "X", "name": "ApplyDefaultMarshalAsAttributeVisitor in assembly", "args": { "durationMS": 26.6363, "detail": "mscorlib" } },
{ "pid": 1, "tid": 1, "ts": 209355, "dur": 2040.6, "ph": "X", "name": "ApplyDefaultMarshalAsAttributeVisitor in assembly", "args": { "durationMS": 2.0406, "detail": "System" } },
{ "pid": 1, "tid": 1, "ts": 211575.8, "dur": 5089.1, "ph": "X", "name": "ApplyDefaultMarshalAsAttributeVisitor in assembly", "args": { "durationMS": 5.0891, "detail": "UnityEngine.CoreModule" } },
{ "pid": 1, "tid": 1, "ts": 217819.8, "dur": 1477.2, "ph": "X", "name": "ApplyDefaultMarshalAsAttributeVisitor in assembly", "args": { "durationMS": 1.4772, "detail": "UnityEngine.UI" } },
{ "pid": 1, "tid": 1, "ts": 219490.8, "dur": 802.8, "ph": "X", "name": "ApplyDefaultMarshalAsAttributeVisitor in assembly", "args": { "durationMS": 0.8028, "detail": "Unity.XR.ARSubsystems" } },
{ "pid": 1, "tid": 1, "ts": 220605.4, "dur": 850.4, "ph": "X", "name": "ApplyDefaultMarshalAsAttributeVisitor in assembly", "args": { "durationMS": 0.8504, "detail": "Unity.XR.ARFoundation" } },
{ "pid": 1, "tid": 1, "ts": 221456.1, "dur": 567.7, "ph": "X", "name": "ApplyDefaultMarshalAsAttributeVisitor in assembly", "args": { "durationMS": 0.5677, "detail": "Unity.XR.ARKit" } },
{ "pid": 1, "tid": 1, "ts": 222034.4, "dur": 4907.5, "ph": "X", "name": "ApplyDefaultMarshalAsAttributeVisitor in assembly", "args": { "durationMS": 4.9075, "detail": "Assembly-CSharp-firstpass" } },
{ "pid": 1, "tid": 1, "ts": 227170.9, "dur": 6460, "ph": "X", "name": "WriteResources", "args": { "durationMS": 6.46, "detail": "" } },
{ "pid": 1, "tid": 1, "ts": 233743.3, "dur": 29817.7, "ph": "X", "name": "CopyEtcFolder", "args": { "durationMS": 29.8177, "detail": "" } },
{ "pid": 1, "tid": 1, "ts": 264333.8, "dur": 192294, "ph": "X", "name": "PreProcessStage", "args": { "durationMS": 192.294, "detail": "" } },
{ "pid": 1, "tid": 1, "ts": 457270.5, "dur": 1232.2, "ph": "X", "name": "Debugger Sequence Points", "args": { "durationMS": 1.2322, "detail": "" } },
{ "pid": 1, "tid": 1, "ts": 459270.8, "dur": 1350174.7, "ph": "X", "name": "Generics Collection", "args": { "durationMS": 1350.1747, "detail": "" } },
{ "pid": 1, "tid": 1, "ts": 459271.9, "dur": 1330862, "ph": "X", "name": "GenericsCollector.Collect", "args": { "durationMS": 1330.862, "detail": "" } },
{ "pid": 1, "tid": 1, "ts": 459939.4, "dur": 13247.9, "ph": "X", "name": "GenericCodeFlowGraphCollector.Collect", "args": { "durationMS": 13.2479, "detail": "" } },
{ "pid": 1, "tid": 1, "ts": 459940.5, "dur": 12706.6, "ph": "X", "name": "GenericCodeFlowGraphCollector.GetTypesAndMethodsForAnalysis", "args": { "durationMS": 12.7066, "detail": "" } },
{ "pid": 1, "tid": 1, "ts": 1790144, "dur": 18286.7, "ph": "X", "name": "CollectGenericVirtualMethods.Collect", "args": { "durationMS": 18.2867, "detail": "" } },
{ "pid": 1, "tid": 1, "ts": 1808433.6, "dur": 802.4, "ph": "X", "name": "AddExtraTypes", "args": { "durationMS": 0.8024, "detail": "" } },
{ "pid": 1, "tid": 1, "ts": 1809447.6, "dur": 1277.7, "ph": "X", "name": "Add Windows Runtime type names", "args": { "durationMS": 1.2777, "detail": "" } },
{ "pid": 1, "tid": 1, "ts": 1811352.4, "dur": 7757438.4, "ph": "X", "name": "AllAssemblyConversion", "args": { "durationMS": 7757.4384, "detail": "" } },
{ "pid": 1, "tid": 1, "ts": 1811917.8, "dur": 3454164.8, "ph": "X", "name": "Convert assembly non-generic methods", "args": { "durationMS": 3454.1648, "detail": "mscorlib" } },
{ "pid": 1, "tid": 1, "ts": 5266084.4, "dur": 6173.8, "ph": "X", "name": "Convert assembly non-generic methods", "args": { "durationMS": 6.1738, "detail": "System.Configuration" } },
{ "pid": 1, "tid": 1, "ts": 5272259.6, "dur": 11469.4, "ph": "X", "name": "Convert assembly non-generic methods", "args": { "durationMS": 11.4694, "detail": "Mono.Security" } },
{ "pid": 1, "tid": 1, "ts": 5283730.8, "dur": 1268.4, "ph": "X", "name": "Convert assembly non-generic methods", "args": { "durationMS": 1.2684, "detail": "System.Xml" } },
{ "pid": 1, "tid": 1, "ts": 5285002, "dur": 377632.3, "ph": "X", "name": "Convert assembly non-generic methods", "args": { "durationMS": 377.6323, "detail": "System" } },
{ "pid": 1, "tid": 1, "ts": 5662635.6, "dur": 1435, "ph": "X", "name": "Convert assembly non-generic methods", "args": { "durationMS": 1.435, "detail": "System.Core" } },
{ "pid": 1, "tid": 1, "ts": 5664072.4, "dur": 17504.4, "ph": "X", "name": "Convert assembly non-generic methods", "args": { "durationMS": 17.5044, "detail": "UnityEngine.SharedInternalsModule" } },
{ "pid": 1, "tid": 1, "ts": 5681578.4, "dur": 654392.8, "ph": "X", "name": "Convert assembly non-generic methods", "args": { "durationMS": 654.3928, "detail": "UnityEngine.CoreModule" } },
{ "pid": 1, "tid": 1, "ts": 6335972.8, "dur": 700.2, "ph": "X", "name": "Convert assembly non-generic methods", "args": { "durationMS": 0.7002, "detail": "UnityEngine.GridModule" } },
{ "pid": 1, "tid": 1, "ts": 6336674.8, "dur": 15853.2, "ph": "X", "name": "Convert assembly non-generic methods", "args": { "durationMS": 15.8532, "detail": "UnityEngine.InputLegacyModule" } },
{ "pid": 1, "tid": 1, "ts": 6352529.6, "dur": 25351.4, "ph": "X", "name": "Convert assembly non-generic methods", "args": { "durationMS": 25.3514, "detail": "UnityEngine.Physics2DModule" } },
{ "pid": 1, "tid": 1, "ts": 6377882.4, "dur": 24289.4, "ph": "X", "name": "Convert assembly non-generic methods", "args": { "durationMS": 24.2894, "detail": "UnityEngine.TextRenderingModule" } },
{ "pid": 1, "tid": 1, "ts": 6402173.6, "dur": 34551.8, "ph": "X", "name": "Convert assembly non-generic methods", "args": { "durationMS": 34.5518, "detail": "UnityEngine.AnimationModule" } },
{ "pid": 1, "tid": 1, "ts": 6436727.2, "dur": 94485.8, "ph": "X", "name": "Convert assembly non-generic methods", "args": { "durationMS": 94.4858, "detail": "UnityEngine.IMGUIModule" } },
{ "pid": 1, "tid": 1, "ts": 6531214.4, "dur": 43758.3, "ph": "X", "name": "Convert assembly non-generic methods", "args": { "durationMS": 43.7583, "detail": "UnityEngine.PhysicsModule" } },
{ "pid": 1, "tid": 1, "ts": 6574974.4, "dur": 678.1, "ph": "X", "name": "Convert assembly non-generic methods", "args": { "durationMS": 0.6781, "detail": "UnityEngine.SpriteShapeModule" } },
{ "pid": 1, "tid": 1, "ts": 6575654, "dur": 13046.3, "ph": "X", "name": "Convert assembly non-generic methods", "args": { "durationMS": 13.0463, "detail": "UnityEngine.SubsystemsModule" } },
{ "pid": 1, "tid": 1, "ts": 6588701.6, "dur": 846.5, "ph": "X", "name": "Convert assembly non-generic methods", "args": { "durationMS": 0.8465, "detail": "UnityEngine.TilemapModule" } },
{ "pid": 1, "tid": 1, "ts": 6589550, "dur": 28136.7, "ph": "X", "name": "Convert assembly non-generic methods", "args": { "durationMS": 28.1367, "detail": "UnityEngine.UIModule" } },
{ "pid": 1, "tid": 1, "ts": 6617688, "dur": 6751.4, "ph": "X", "name": "Convert assembly non-generic methods", "args": { "durationMS": 6.7514, "detail": "Unity.Subsystem.Registration" } },
{ "pid": 1, "tid": 1, "ts": 6624441.2, "dur": 2809, "ph": "X", "name": "Convert assembly non-generic methods", "args": { "durationMS": 2.809, "detail": "UnityEngine.AIModule" } },
{ "pid": 1, "tid": 1, "ts": 6627251.6, "dur": 2152, "ph": "X", "name": "Convert assembly non-generic methods", "args": { "durationMS": 2.152, "detail": "UnityEngine.ARModule" } },
{ "pid": 1, "tid": 1, "ts": 6629404.8, "dur": 12757.4, "ph": "X", "name": "Convert assembly non-generic methods", "args": { "durationMS": 12.7574, "detail": "UnityEngine.AudioModule" } },
{ "pid": 1, "tid": 1, "ts": 6642164, "dur": 25587.9, "ph": "X", "name": "Convert assembly non-generic methods", "args": { "durationMS": 25.5879, "detail": "UnityEngine.ParticleSystemModule" } },
{ "pid": 1, "tid": 1, "ts": 6667753.2, "dur": 929617.1, "ph": "X", "name": "Convert assembly non-generic methods", "args": { "durationMS": 929.6171, "detail": "UnityEngine.UI" } },
{ "pid": 1, "tid": 1, "ts": 7597373.6, "dur": 3193.5, "ph": "X", "name": "Convert assembly non-generic methods", "args": { "durationMS": 3.1935, "detail": "UnityEngine.VehiclesModule" } },
{ "pid": 1, "tid": 1, "ts": 7600568, "dur": 54987.3, "ph": "X", "name": "Convert assembly non-generic methods", "args": { "durationMS": 54.9873, "detail": "UnityEngine.XRModule" } },
{ "pid": 1, "tid": 1, "ts": 7655556.8, "dur": 477807.9, "ph": "X", "name": "Convert assembly non-generic methods", "args": { "durationMS": 477.8079, "detail": "Unity.XR.ARSubsystems" } },
{ "pid": 1, "tid": 1, "ts": 8133366.4, "dur": 20214.4, "ph": "X", "name": "Convert assembly non-generic methods", "args": { "durationMS": 20.2144, "detail": "Unity.XR.Management" } },
{ "pid": 1, "tid": 1, "ts": 8153582.4, "dur": 46121.3, "ph": "X", "name": "Convert assembly non-generic methods", "args": { "durationMS": 46.1213, "detail": "UnityEngine.GameCenterModule" } },
{ "pid": 1, "tid": 1, "ts": 8199705.6, "dur": 4424.4, "ph": "X", "name": "Convert assembly non-generic methods", "args": { "durationMS": 4.4244, "detail": "UnityEngine.InputModule" } },
{ "pid": 1, "tid": 1, "ts": 8204131.2, "dur": 23773.8, "ph": "X", "name": "Convert assembly non-generic methods", "args": { "durationMS": 23.7738, "detail": "UnityEngine.SpatialTracking" } },
{ "pid": 1, "tid": 1, "ts": 8227907.2, "dur": 591338.4, "ph": "X", "name": "Convert assembly non-generic methods", "args": { "durationMS": 591.3384, "detail": "Unity.XR.ARFoundation" } },
{ "pid": 1, "tid": 1, "ts": 8819247.2, "dur": 184388.7, "ph": "X", "name": "Convert assembly non-generic methods", "args": { "durationMS": 184.3887, "detail": "Unity.XR.ARKit" } },
{ "pid": 1, "tid": 1, "ts": 9003638.4, "dur": 487.8, "ph": "X", "name": "Convert assembly non-generic methods", "args": { "durationMS": 0.4878, "detail": "UnityEngine" } },
{ "pid": 1, "tid": 1, "ts": 9004127.2, "dur": 517376.3, "ph": "X", "name": "Convert assembly non-generic methods", "args": { "durationMS": 517.3763, "detail": "Assembly-CSharp-firstpass" } },
{ "pid": 1, "tid": 1, "ts": 9521505.6, "dur": 47283.6, "ph": "X", "name": "Convert assembly non-generic methods", "args": { "durationMS": 47.2836, "detail": "Assembly-CSharp" } },
{ "pid": 1, "tid": 1, "ts": 9568952, "dur": 4298971.2, "ph": "X", "name": "WriteGenerics", "args": { "durationMS": 4298.9712, "detail": "" } },
{ "pid": 1, "tid": 1, "ts": 9570048.8, "dur": 785415, "ph": "X", "name": "GenericInstanceMethods", "args": { "durationMS": 785.415, "detail": "" } },
{ "pid": 1, "tid": 1, "ts": 10355471.2, "dur": 3227003.2, "ph": "X", "name": "GenericInstanceTypes", "args": { "durationMS": 3227.0032, "detail": "" } },
{ "pid": 1, "tid": 1, "ts": 13582596.8, "dur": 285292.3, "ph": "X", "name": "GenericComDefinitions", "args": { "durationMS": 285.2923, "detail": "" } },
{ "pid": 1, "tid": 1, "ts": 13868176, "dur": 642.3, "ph": "X", "name": "Executable Processing", "args": { "durationMS": 0.6423, "detail": "" } },
{ "pid": 1, "tid": 1, "ts": 13870001.6, "dur": 280134.3, "ph": "X", "name": "MetadataCollector", "args": { "durationMS": 280.1343, "detail": "" } },
{ "pid": 1, "tid": 1, "ts": 13871425.6, "dur": 13189.3, "ph": "X", "name": "UpdateEmptyTokens", "args": { "durationMS": 13.1893, "detail": "" } },
{ "pid": 1, "tid": 1, "ts": 13885968, "dur": 16907.6, "ph": "X", "name": "ValidateTokens", "args": { "durationMS": 16.9076, "detail": "" } },
{ "pid": 1, "tid": 1, "ts": 14150614.4, "dur": 1752.9, "ph": "X", "name": "Write COM Callable Wrappers", "args": { "durationMS": 1.7529, "detail": "" } },
{ "pid": 1, "tid": 1, "ts": 14152451.2, "dur": 474.4, "ph": "X", "name": "Write Windows Runtime Factories", "args": { "durationMS": 0.4744, "detail": "" } },
{ "pid": 1, "tid": 1, "ts": 14153211.2, "dur": 2662065, "ph": "X", "name": "Metadata", "args": { "durationMS": 2662.065, "detail": "Global" } },
{ "pid": 1, "tid": 1, "ts": 14215868.8, "dur": 922268.8, "ph": "X", "name": "Il2CppAttributes.cpp", "args": { "durationMS": 922.2688, "detail": "" } },
{ "pid": 1, "tid": 1, "ts": 15301673.6, "dur": 17041.8, "ph": "X", "name": "UnresolvedVirtualCallStubs.cpp", "args": { "durationMS": 17.0418, "detail": "" } },
{ "pid": 1, "tid": 1, "ts": 15320448, "dur": 441967.2, "ph": "X", "name": "WriteCodeRegistration", "args": { "durationMS": 441.9672, "detail": "" } },
{ "pid": 1, "tid": 1, "ts": 15320480, "dur": 81643.9, "ph": "X", "name": "mscorlib_CodeGen.c", "args": { "durationMS": 81.6439, "detail": "" } },
{ "pid": 1, "tid": 1, "ts": 15391489.6, "dur": 2979.5, "ph": "X", "name": "GenericContextCollector", "args": { "durationMS": 2.9795, "detail": "Collect" } },
{ "pid": 1, "tid": 1, "ts": 15402137.6, "dur": 715, "ph": "X", "name": "System.Configuration_CodeGen.c", "args": { "durationMS": 0.715, "detail": "" } },
{ "pid": 1, "tid": 1, "ts": 15402862.4, "dur": 550.5, "ph": "X", "name": "Mono.Security_CodeGen.c", "args": { "durationMS": 0.5505, "detail": "" } },
{ "pid": 1, "tid": 1, "ts": 15403758.4, "dur": 6696.7, "ph": "X", "name": "System_CodeGen.c", "args": { "durationMS": 6.6967, "detail": "" } },
{ "pid": 1, "tid": 1, "ts": 15410465.6, "dur": 877.2, "ph": "X", "name": "System.Core_CodeGen.c", "args": { "durationMS": 0.8772, "detail": "" } },
{ "pid": 1, "tid": 1, "ts": 15411352, "dur": 852.4, "ph": "X", "name": "UnityEngine.SharedInternalsModule_CodeGen.c", "args": { "durationMS": 0.8524, "detail": "" } },
{ "pid": 1, "tid": 1, "ts": 15412212.8, "dur": 16409.5, "ph": "X", "name": "UnityEngine.CoreModule_CodeGen.c", "args": { "durationMS": 16.4095, "detail": "" } },
{ "pid": 1, "tid": 1, "ts": 15426552, "dur": 455.5, "ph": "X", "name": "GenericContextCollector", "args": { "durationMS": 0.4555, "detail": "Collect" } },
{ "pid": 1, "tid": 1, "ts": 15428633.6, "dur": 352.4, "ph": "X", "name": "UnityEngine.GridModule_CodeGen.c", "args": { "durationMS": 0.3524, "detail": "" } },
{ "pid": 1, "tid": 1, "ts": 15428995.2, "dur": 761.6, "ph": "X", "name": "UnityEngine.InputLegacyModule_CodeGen.c", "args": { "durationMS": 0.7616, "detail": "" } },
{ "pid": 1, "tid": 1, "ts": 15429764.8, "dur": 1052.9, "ph": "X", "name": "UnityEngine.Physics2DModule_CodeGen.c", "args": { "durationMS": 1.0529, "detail": "" } },
{ "pid": 1, "tid": 1, "ts": 15430825.6, "dur": 836.3, "ph": "X", "name": "UnityEngine.TextRenderingModule_CodeGen.c", "args": { "durationMS": 0.8363, "detail": "" } },
{ "pid": 1, "tid": 1, "ts": 15431672, "dur": 1139.2, "ph": "X", "name": "UnityEngine.AnimationModule_CodeGen.c", "args": { "durationMS": 1.1392, "detail": "" } },
{ "pid": 1, "tid": 1, "ts": 15432819.2, "dur": 1791.6, "ph": "X", "name": "UnityEngine.IMGUIModule_CodeGen.c", "args": { "durationMS": 1.7916, "detail": "" } },
{ "pid": 1, "tid": 1, "ts": 15434619.2, "dur": 2298.3, "ph": "X", "name": "UnityEngine.PhysicsModule_CodeGen.c", "args": { "durationMS": 2.2983, "detail": "" } },
{ "pid": 1, "tid": 1, "ts": 15436926.4, "dur": 390, "ph": "X", "name": "UnityEngine.SpriteShapeModule_CodeGen.c", "args": { "durationMS": 0.39, "detail": "" } },
{ "pid": 1, "tid": 1, "ts": 15437326.4, "dur": 701.2, "ph": "X", "name": "UnityEngine.SubsystemsModule_CodeGen.c", "args": { "durationMS": 0.7012, "detail": "" } },
{ "pid": 1, "tid": 1, "ts": 15438035.2, "dur": 383, "ph": "X", "name": "UnityEngine.TilemapModule_CodeGen.c", "args": { "durationMS": 0.383, "detail": "" } },
{ "pid": 1, "tid": 1, "ts": 15438430.4, "dur": 1194.3, "ph": "X", "name": "UnityEngine.UIModule_CodeGen.c", "args": { "durationMS": 1.1943, "detail": "" } },
{ "pid": 1, "tid": 1, "ts": 15439633.6, "dur": 376, "ph": "X", "name": "Unity.Subsystem.Registration_CodeGen.c", "args": { "durationMS": 0.376, "detail": "" } },
{ "pid": 1, "tid": 1, "ts": 15440017.6, "dur": 423.2, "ph": "X", "name": "UnityEngine.AIModule_CodeGen.c", "args": { "durationMS": 0.4232, "detail": "" } },
{ "pid": 1, "tid": 1, "ts": 15440449.6, "dur": 517.1, "ph": "X", "name": "UnityEngine.ARModule_CodeGen.c", "args": { "durationMS": 0.5171, "detail": "" } },
{ "pid": 1, "tid": 1, "ts": 15440976, "dur": 896.4, "ph": "X", "name": "UnityEngine.AudioModule_CodeGen.c", "args": { "durationMS": 0.8964, "detail": "" } },
{ "pid": 1, "tid": 1, "ts": 15441881.6, "dur": 975.2, "ph": "X", "name": "UnityEngine.ParticleSystemModule_CodeGen.c", "args": { "durationMS": 0.9752, "detail": "" } },
{ "pid": 1, "tid": 1, "ts": 15442865.6, "dur": 13412.4, "ph": "X", "name": "UnityEngine.UI_CodeGen.c", "args": { "durationMS": 13.4124, "detail": "" } },
{ "pid": 1, "tid": 1, "ts": 15456289.6, "dur": 384.8, "ph": "X", "name": "UnityEngine.VehiclesModule_CodeGen.c", "args": { "durationMS": 0.3848, "detail": "" } },
{ "pid": 1, "tid": 1, "ts": 15456683.2, "dur": 1123.6, "ph": "X", "name": "UnityEngine.XRModule_CodeGen.c", "args": { "durationMS": 1.1236, "detail": "" } },
{ "pid": 1, "tid": 1, "ts": 15457816, "dur": 9445.9, "ph": "X", "name": "Unity.XR.ARSubsystems_CodeGen.c", "args": { "durationMS": 9.4459, "detail": "" } },
{ "pid": 1, "tid": 1, "ts": 15467273.6, "dur": 721.1, "ph": "X", "name": "Unity.XR.Management_CodeGen.c", "args": { "durationMS": 0.7211, "detail": "" } },
{ "pid": 1, "tid": 1, "ts": 15468003.2, "dur": 1576.7, "ph": "X", "name": "UnityEngine.GameCenterModule_CodeGen.c", "args": { "durationMS": 1.5767, "detail": "" } },
{ "pid": 1, "tid": 1, "ts": 15469590.4, "dur": 429.4, "ph": "X", "name": "UnityEngine.InputModule_CodeGen.c", "args": { "durationMS": 0.4294, "detail": "" } },
{ "pid": 1, "tid": 1, "ts": 15470027.2, "dur": 654.9, "ph": "X", "name": "UnityEngine.SpatialTracking_CodeGen.c", "args": { "durationMS": 0.6549, "detail": "" } },
{ "pid": 1, "tid": 1, "ts": 15470691.2, "dur": 9759.8, "ph": "X", "name": "Unity.XR.ARFoundation_CodeGen.c", "args": { "durationMS": 9.7598, "detail": "" } },
{ "pid": 1, "tid": 1, "ts": 15480462.4, "dur": 3820.3, "ph": "X", "name": "Unity.XR.ARKit_CodeGen.c", "args": { "durationMS": 3.8203, "detail": "" } },
{ "pid": 1, "tid": 1, "ts": 15484611.2, "dur": 5845.9, "ph": "X", "name": "Assembly-CSharp-firstpass_CodeGen.c", "args": { "durationMS": 5.8459, "detail": "" } },
{ "pid": 1, "tid": 1, "ts": 15490468.8, "dur": 820.9, "ph": "X", "name": "Assembly-CSharp_CodeGen.c", "args": { "durationMS": 0.8209, "detail": "" } },
{ "pid": 1, "tid": 1, "ts": 15491908.8, "dur": 946.6, "ph": "X", "name": "Il2CppReversePInvokeWrapperTable.cpp", "args": { "durationMS": 0.9466, "detail": "" } },
{ "pid": 1, "tid": 1, "ts": 15493017.6, "dur": 109153, "ph": "X", "name": "Il2CppGenericMethodPointerTable.cpp", "args": { "durationMS": 109.153, "detail": "" } },
{ "pid": 1, "tid": 1, "ts": 15602323.2, "dur": 135045.5, "ph": "X", "name": "Il2CppInvokerTable.cpp", "args": { "durationMS": 135.0455, "detail": "" } },
{ "pid": 1, "tid": 1, "ts": 15737926.4, "dur": 21913.7, "ph": "X", "name": "Il2CppInteropDataTable.cpp", "args": { "durationMS": 21.9137, "detail": "" } },
{ "pid": 1, "tid": 1, "ts": 15761513.6, "dur": 899.9, "ph": "X", "name": "Il2CppCodeRegistration.cpp", "args": { "durationMS": 0.8999, "detail": "" } },
{ "pid": 1, "tid": 1, "ts": 15762419.2, "dur": 1052856.2, "ph": "X", "name": "WriteMetadata", "args": { "durationMS": 1052.8562, "detail": "" } },
{ "pid": 1, "tid": 1, "ts": 15767168, "dur": 187044.8, "ph": "X", "name": "Il2CppMetadataUsage.c", "args": { "durationMS": 187.0448, "detail": "" } },
{ "pid": 1, "tid": 1, "ts": 15841006.4, "dur": 3641.9, "ph": "X", "name": "Metadata", "args": { "durationMS": 3.6419, "detail": "Collect string literals" } },
{ "pid": 1, "tid": 1, "ts": 15967782.4, "dur": 22120.1, "ph": "X", "name": "Il2CppGenericClassTable.c", "args": { "durationMS": 22.1201, "detail": "" } },
{ "pid": 1, "tid": 1, "ts": 15989918.4, "dur": 28523.2, "ph": "X", "name": "Il2CppGenericInstDefinitions.c", "args": { "durationMS": 28.5232, "detail": "" } },
{ "pid": 1, "tid": 1, "ts": 16018457.6, "dur": 325278.9, "ph": "X", "name": "Il2CppGenericMethodTable.c", "args": { "durationMS": 325.2789, "detail": "" } },
{ "pid": 1, "tid": 1, "ts": 16343756.8, "dur": 86289, "ph": "X", "name": "Il2CppTypeDefinitions.c", "args": { "durationMS": 86.289, "detail": "" } },
{ "pid": 1, "tid": 1, "ts": 16430067.2, "dur": 59823.1, "ph": "X", "name": "Il2CppGenericMethodDefinitions.c", "args": { "durationMS": 59.8231, "detail": "" } },
{ "pid": 1, "tid": 1, "ts": 16489900.8, "dur": 137089.6, "ph": "X", "name": "CompilerCalculateTypeValues", "args": { "durationMS": 137.0896, "detail": "" } },
{ "pid": 1, "tid": 1, "ts": 16627006.4, "dur": 1577.5, "ph": "X", "name": "Il2CppMetadataRegistration.c", "args": { "durationMS": 1.5775, "detail": "" } },
{ "pid": 1, "tid": 1, "ts": 16628915.2, "dur": 6687.7, "ph": "X", "name": "StringLiteralWriter", "args": { "durationMS": 6.6877, "detail": "" } },
{ "pid": 1, "tid": 1, "ts": 16635731.2, "dur": 842.8, "ph": "X", "name": "Metadata Strings", "args": { "durationMS": 0.8428, "detail": "" } },
{ "pid": 1, "tid": 1, "ts": 16636579.2, "dur": 4503.8, "ph": "X", "name": "Events", "args": { "durationMS": 4.5038, "detail": "" } },
{ "pid": 1, "tid": 1, "ts": 16641088, "dur": 8262.3, "ph": "X", "name": "Properties", "args": { "durationMS": 8.2623, "detail": "" } },
{ "pid": 1, "tid": 1, "ts": 16649356.8, "dur": 54584.4, "ph": "X", "name": "Methods", "args": { "durationMS": 54.5844, "detail": "" } },
{ "pid": 1, "tid": 1, "ts": 16703952, "dur": 3563.2, "ph": "X", "name": "Parameter Default Values", "args": { "durationMS": 3.5632, "detail": "" } },
{ "pid": 1, "tid": 1, "ts": 16707521.6, "dur": 3939.3, "ph": "X", "name": "Field Default Values", "args": { "durationMS": 3.9393, "detail": "" } },
{ "pid": 1, "tid": 1, "ts": 16711660.8, "dur": 423.6, "ph": "X", "name": "Field Marshaled Sizes", "args": { "durationMS": 0.4236, "detail": "" } },
{ "pid": 1, "tid": 1, "ts": 16712088, "dur": 13780.1, "ph": "X", "name": "Parameters", "args": { "durationMS": 13.7801, "detail": "" } },
{ "pid": 1, "tid": 1, "ts": 16725876.8, "dur": 9344.6, "ph": "X", "name": "Fields", "args": { "durationMS": 9.3446, "detail": "" } },
{ "pid": 1, "tid": 1, "ts": 16735230.4, "dur": 3594.3, "ph": "X", "name": "Generic Parameters", "args": { "durationMS": 3.5943, "detail": "" } },
{ "pid": 1, "tid": 1, "ts": 16738830.4, "dur": 765.9, "ph": "X", "name": "Generic Parameter Constraints", "args": { "durationMS": 0.7659, "detail": "" } },
{ "pid": 1, "tid": 1, "ts": 16739601.6, "dur": 3388.3, "ph": "X", "name": "Generic Containers", "args": { "durationMS": 3.3883, "detail": "" } },
{ "pid": 1, "tid": 1, "ts": 16743388.8, "dur": 1899.2, "ph": "X", "name": "VTables", "args": { "durationMS": 1.8992, "detail": "" } },
{ "pid": 1, "tid": 1, "ts": 16745296, "dur": 1246, "ph": "X", "name": "Interface Offsets", "args": { "durationMS": 1.246, "detail": "" } },
{ "pid": 1, "tid": 1, "ts": 16746548.8, "dur": 47301.7, "ph": "X", "name": "Type Definitions", "args": { "durationMS": 47.3017, "detail": "" } },
{ "pid": 1, "tid": 1, "ts": 16793864, "dur": 5613.7, "ph": "X", "name": "Images", "args": { "durationMS": 5.6137, "detail": "" } },
{ "pid": 1, "tid": 1, "ts": 16799483.2, "dur": 3671.1, "ph": "X", "name": "Assemblies", "args": { "durationMS": 3.6711, "detail": "" } },
{ "pid": 1, "tid": 1, "ts": 16803161.6, "dur": 849.5, "ph": "X", "name": "Metadata Usage Lists", "args": { "durationMS": 0.8495, "detail": "" } },
{ "pid": 1, "tid": 1, "ts": 16804016, "dur": 2229.1, "ph": "X", "name": "Metadata Usage Pairs", "args": { "durationMS": 2.2291, "detail": "" } },
{ "pid": 1, "tid": 1, "ts": 16806392, "dur": 496, "ph": "X", "name": "Referenced Assemblies", "args": { "durationMS": 0.496, "detail": "" } },
{ "pid": 1, "tid": 1, "ts": 16806892.8, "dur": 1035.3, "ph": "X", "name": "Attribute Types Ranges", "args": { "durationMS": 1.0353, "detail": "" } },
{ "pid": 1, "tid": 1, "ts": 16807932.8, "dur": 475.3, "ph": "X", "name": "Attribute Types", "args": { "durationMS": 0.4753, "detail": "" } },
{ "pid": 1, "tid": 1, "ts": 16808555.2, "dur": 514.8, "ph": "X", "name": "Unresolved Virtual Call Parameter Ranges", "args": { "durationMS": 0.5148, "detail": "" } },
{ "pid": 1, "tid": 1, "ts": 16809264, "dur": 3985.5, "ph": "X", "name": "Exported Types", "args": { "durationMS": 3.9855, "detail": "" } },
{ "pid": 1, "tid": 1, "ts": 16815448, "dur": 697.2, "ph": "X", "name": "CompletionPhase", "args": { "durationMS": 0.6972, "detail": "" } }
],
"meta_datetime": "11/17/2020 15:05:05",
"meta_command_line": "/Applications/Unity/Hub/Editor/2020.1.13f1/Unity.app/Contents/il2cpp/build/deploy/net471/il2cpp.exe --convert-to-cpp --emit-null-checks --enable-array-bounds-check --dotnetprofile=unityaot --incremental-g-c-time-slice=3 --avoid-dynamic-library-copy --profiler-report --map-file-parser=/Applications/Unity/Hub/Editor/2020.1.13f1/Unity.app/Contents/Tools/MapFileParser/MapFileParser --directory=/Users/timnevidim/Documents/\u0423\u0447\u0435\u0431\u0430/Unity/\u0410\u0440\u0445\u0438\u0442\u0435\u043a\u0442\u0443\u0440\u0430/PortalXR_iOS/Temp/StagingArea/Data/Managed --generatedcppdir=/Users/timnevidim/Documents/\u0423\u0447\u0435\u0431\u0430/Unity/\u0410\u0440\u0445\u0438\u0442\u0435\u043a\u0442\u0443\u0440\u0430/PortalXR_iOS/Temp/il2cppOutput/il2cppOutput",
"meta_command_line_args": "/Applications/Unity/Hub/Editor/2020.1.13f1/Unity.app/Contents/il2cpp/build/deploy/net471/il2cpp.exe --convert-to-cpp --emit-null-checks --enable-array-bounds-check --dotnetprofile=unityaot --incremental-g-c-time-slice=3 --avoid-dynamic-library-copy --profiler-report --map-file-parser=/Applications/Unity/Hub/Editor/2020.1.13f1/Unity.app/Contents/Tools/MapFileParser/MapFileParser --directory=/Users/timnevidim/Documents/\u0423\u0447\u0435\u0431\u0430/Unity/\u0410\u0440\u0445\u0438\u0442\u0435\u043a\u0442\u0443\u0440\u0430/PortalXR_iOS/Temp/StagingArea/Data/Managed --generatedcppdir=/Users/timnevidim/Documents/\u0423\u0447\u0435\u0431\u0430/Unity/\u0410\u0440\u0445\u0438\u0442\u0435\u043a\u0442\u0443\u0440\u0430/PortalXR_iOS/Temp/il2cppOutput/il2cppOutput",
"meta_user_name": "timnevidim",
"meta_os_version": "Unix 19.6.0.0",
"meta_cpu_count": "8"}
